codemapper/.DS_Store
codemapper/__init__.py
codemapper/builders/__init__.py
codemapper/builders/build_codemap.py
codemapper/builders/build_docmap.py
codemapper/builders/build_markdown.py
codemapper/cli.py
codemapper/config.py
codemapper/help.py
codemapper/processors/__init__.py
codemapper/processors/process_dir.py
codemapper/processors/process_git.py
codemapper/readers/__init__.py
codemapper/readers/detect_types.py
codemapper/readers/read_files.py
codemapper/readers/scan_paths.py
codemapper/types.py
codemapper/writers/__init__.py
codemapper/writers/manage_output.py
codemapper-4.8.1.dist-info/WHEEL
codemapper-4.8.1.dist-info/entry_points.txt
codemapper-4.8.1.dist-info/METADATA
codemapper-4.8.1.dist-info/RECORD
