Metadata-Version: 2.3
Name: codemapper
Version: 4.8.1
Summary: A tool to generate comprehensive Markdown artifacts of directory structures and file contents
Keywords: codemapper,markdown,directory,file contents
Author: Shane Holloman
Author-email: Shane Holloman <shaneholloman@gmail.com>
License: MIT License
Classifier: Development Status :: 4 - Beta
Classifier: Intended Audience :: Developers
Classifier: License :: OSI Approved :: MIT License
Classifier: Operating System :: OS Independent
Classifier: Programming Language :: Python :: 3.12
Classifier: Programming Language :: Python :: 3.13
Requires-Dist: chardet
Requires-Dist: pathspec
Requires-Dist: ruff ; extra == 'dev'
Requires-Dist: ty ; extra == 'dev'
Requires-Dist: pytest ; extra == 'dev'
Requires-Python: >=3.12
Project-URL: Homepage, https://github.com/shaneholloman/codemapper
Provides-Extra: dev
